evoagentx/__init__.py
evoagentx/config.py
evoagentx/actions/__init__.py
evoagentx/actions/action.py
evoagentx/actions/agent_generation.py
evoagentx/actions/code_extraction.py
evoagentx/actions/code_verification.py
evoagentx/actions/customize_action.py
evoagentx/actions/task_planning.py
evoagentx/agents/__init__.py
evoagentx/agents/action_agent.py
evoagentx/agents/agent.py
evoagentx/agents/agent_generator.py
evoagentx/agents/agent_manager.py
evoagentx/agents/customize_agent.py
evoagentx/agents/long_term_memory_agent.py
evoagentx/agents/task_planner.py
evoagentx/agents/workflow_reviewer.py
evoagentx/app/__init__.py
evoagentx/app/api.py
evoagentx/app/config.py
evoagentx/app/db.py
evoagentx/app/main.py
evoagentx/app/schemas.py
evoagentx/app/security.py
evoagentx/app/services.py
evoagentx/benchmark/WorfBench.py
evoagentx/benchmark/__init__.py
evoagentx/benchmark/benchmark.py
evoagentx/benchmark/gsm8k.py
evoagentx/benchmark/hotpotqa.py
evoagentx/benchmark/humaneval.py
evoagentx/benchmark/livecodebench.py
evoagentx/benchmark/math_benchmark.py
evoagentx/benchmark/mbpp.py
evoagentx/benchmark/measures.py
evoagentx/benchmark/nq.py
evoagentx/benchmark/lcb_utils/__init__.py
evoagentx/benchmark/lcb_utils/code_execution.py
evoagentx/benchmark/lcb_utils/code_generation.py
evoagentx/benchmark/lcb_utils/evaluation.py
evoagentx/benchmark/lcb_utils/test_output_prediction.py
evoagentx/benchmark/lcb_utils/utils.py
evoagentx/core/__init__.py
evoagentx/core/base_config.py
evoagentx/core/callbacks.py
evoagentx/core/decorators.py
evoagentx/core/logging.py
evoagentx/core/message.py
evoagentx/core/module.py
evoagentx/core/module_utils.py
evoagentx/core/parser.py
evoagentx/core/registry.py
evoagentx/evaluators/__init__.py
evoagentx/evaluators/aflow_evaluator.py
evoagentx/evaluators/evaluator.py
evoagentx/hitl/__init__.py
evoagentx/hitl/approval_manager.py
evoagentx/hitl/hitl.py
evoagentx/hitl/hitl_gui.py
evoagentx/hitl/interceptor_agent.py
evoagentx/hitl/special_hitl_agent.py
evoagentx-0.1.0.dist-info/licenses/LICENSE
evoagentx-0.1.0.dist-info/METADATA
evoagentx-0.1.0.dist-info/WHEEL
evoagentx-0.1.0.dist-info/top_level.txt
evoagentx-0.1.0.dist-info/RECORD
