Metadata-Version: 2.4
Name: evoagentx
Version: 0.1.0
Summary: A framework for evolving agentic workflows with LLMs.
Author-email: EvoAgentX Team <evoagentx.ai@gmail.com>
License: MIT
Project-URL: Homepage, https://github.com/EvoAgentX/EvoAgentX
Project-URL: Documentation, https://EvoAgentX.github.io/EvoAgentX/
Project-URL: Repository, https://github.com/EvoAgentX/EvoAgentX
Classifier: Programming Language :: Python :: 3
Classifier: License :: OSI Approved :: MIT License
Classifier: Operating System :: OS Independent
Requires-Python: >=3.10
License-File: LICENSE
Requires-Dist: sympy
Requires-Dist: overdue
Requires-Dist: scipy
Requires-Dist: setuptools
Requires-Dist: tree_sitter
Requires-Dist: tree_sitter_python
Requires-Dist: antlr4-python3-runtime==4.11
Requires-Dist: tenacity
Requires-Dist: networkx>=3.3
Requires-Dist: nltk>=3.9.1
Requires-Dist: numpy>=1.26.4
Requires-Dist: openai>=1.55.3
Requires-Dist: litellm>=1.55.6
Requires-Dist: pydantic>=2.9.0
Requires-Dist: loguru>=0.7.3
Requires-Dist: pandas>=2.2.3
Requires-Dist: matplotlib>=3.10.0
Requires-Dist: transformers>=4.47.1
Requires-Dist: datasets>=3.4.0
Requires-Dist: faiss-cpu==1.8.0.post1
Requires-Dist: docker>=6.1.2
Requires-Dist: fastapi>=0.115.11
Requires-Dist: motor>=3.7.0
Requires-Dist: uvicorn>=0.34.0
Requires-Dist: sqlalchemy>=2.0.38
Requires-Dist: python-jose>=3.3.0
Requires-Dist: passlib>=1.7.4
Requires-Dist: python-multipart>=0.0.6
Requires-Dist: bcrypt>=4.0.1
Requires-Dist: celery>=5.3.4
Requires-Dist: redis>=5.0.0
Requires-Dist: httpx>=0.24.1
Requires-Dist: asgi-lifespan>=1.0.1
Requires-Dist: python-dotenv>=1.0.0
Requires-Dist: jwt>=1.3.1
Requires-Dist: dashscope>=1.23.4
Requires-Dist: textgrad>=0.1.8
Requires-Dist: dspy
Requires-Dist: googlesearch-python
Requires-Dist: wikipedia
Requires-Dist: mcp
Requires-Dist: beautifulsoup4
Requires-Dist: neo4j
Requires-Dist: ollama
Requires-Dist: llama-index
Requires-Dist: llama-index-vector-stores-faiss
Requires-Dist: llama-index-graph-stores-neo4j
Requires-Dist: sentence-transformers
Requires-Dist: docx2txt
Requires-Dist: python-pptx
Requires-Dist: Pillow
Requires-Dist: PyPDF2
Requires-Dist: selenium
Requires-Dist: html2text
Requires-Dist: fastmcp
Provides-Extra: dev
Requires-Dist: pytest; extra == "dev"
Requires-Dist: pytest-cov; extra == "dev"
Requires-Dist: pytest-mock; extra == "dev"
Requires-Dist: pytest-asyncio; extra == "dev"
Requires-Dist: pytest-subtests; extra == "dev"
Requires-Dist: pytest-json-report; extra == "dev"
Requires-Dist: ruff; extra == "dev"
Dynamic: license-file
